parsec/__init__.py
parsec/__init__.pyi
parsec/py.typed
parsec/tests/__init__.py
parsec/tests/test_parsec.py
parsec/tests/python_3_only/__init__.py
parsec/tests/python_3_only/test_generator.py
parsec-3.13.dist-info/LICENSE
parsec-3.13.dist-info/METADATA
parsec-3.13.dist-info/WHEEL
parsec-3.13.dist-info/top_level.txt
parsec-3.13.dist-info/RECORD
